helloworldfromodou.py
helloworldfromodou-0.0.1.dist-info/LICENCE.txt
helloworldfromodou-0.0.1.dist-info/METADATA
helloworldfromodou-0.0.1.dist-info/WHEEL
helloworldfromodou-0.0.1.dist-info/top_level.txt
helloworldfromodou-0.0.1.dist-info/RECORD
