Metadata-Version: 2.1
Name: helloworldfromodou
Version: 0.0.1
Summary: Say Hello world
Home-page: https://github.com/Modiao/setup_pytest
Author: Modou Diao
Author-email: diaomodou06@gmail.com
License: UNKNOWN
Platform: UNKNOWN
Classifier: Programming Language :: Python :: 3
Classifier: Programming Language :: Python :: 3.6
Classifier: Programming Language :: Python :: 3.7
Classifier: Operating System :: OS Independent
Classifier: License :: OSI Approved :: GNU Affero General Public License v3
License-File: LICENCE.txt
Requires-Dist: blessings (==1.7)
Provides-Extra: dev
Requires-Dist: pytest (>=3.7) ; extra == 'dev'
Requires-Dist: check-manifest ; extra == 'dev'
Requires-Dist: twine ; extra == 'dev'
